geortree
