Metadata-Version: 2.1
Name: geortree
Version: 0.7.1
Summary: Reasonably efficient R-Tree implementation, adapted to work with geographic coordinates.
Home-page: https://github.com/GFlorio/geortree
Author: Gabriel Florio
Author-email: gabriel@gabrielflorio.com
License: MIT
Platform: UNKNOWN
Classifier: Development Status :: 4 - Beta
Classifier: Intended Audience :: Developers
Classifier: License :: OSI Approved :: MIT License
Classifier: Programming Language :: Python :: 3
Classifier: Programming Language :: Python :: 3.7
Classifier: Programming Language :: Python :: 3.8
